Workbook

Sheet License Agreement
S1: ©2021 ROHM Co., LTD.
B2: 本ツールの使用にあたっては、お客様は以下の使用許諾内容に合意しています。 | S2: 20200319
B3: 使用許諾内容に合意できない場合は、本ツールの使用はできませんので、破棄してください。
B4: In using this tool, you have agreed to the following license agreement.
B5: If you do not agree, you will not be able to use this tool. In such case, you shall destroy this tool.
B7: **************************************************************************************************
B9: ツール使用許諾書
B11: 第1条 用語の定義
B12: 1.「お客様」とは、本契約の条件に従って「本ツール」を使用するユーザーを意味します。
B13: 2.「弊社」とは、ローム株式会社及びローム関連会社（該当する場合には）を意味します。
B14: 3.「本ツール」とは、弊社の製品を使った設計をサポートする、技術資料、計算シート、各種モデル、シュミレーターおよびそれらに関するドキュメントを意味します。
B16: 第2条 使用許諾
B17: 1.弊社は、本使用許諾書に同意したお客様に対して、本ツールをダウンロードして使用する非独占的で譲渡不能な権利を許諾致します。
B18: 本使用許諾書は、本ツールの修正版、アップデート版、またコピーされたものにも適用されるものとします。
... B110: **************************************************************************************************

Sheet How to use
A1: BD9G500EFJ-LA Calculation Sheet | M1: REV.001 20210827
M2: ©2021 ROHM Co., LTD.
A3: Before you start
C4: この度はロームのCalculation Sheetをダウンロードいただきありがとうございます。本シートではスイッチングレギュレータ製品をお使いいただくにあたって必要となる外付け部品の定数計算をExcelスプレッドシートに集約しております。ご不明点などございましたらロームの営業担当者までご連絡ください。
C5: Thank you for downloading ROHM's Calculation Sheet. This sheet is an Excel spreadsheet for calculating the constants of external components required for using switching regulator products. If you have any questions, please contact your ROHM sales representative.
C6: ご使用にあたって必ず最新のデータシートをロームホームページ下記のURLからダウンロードいただき、内容をよくご確認くださいますようお願いいたします。
C7: Before using the product, be sure to download the latest datasheet from the following URL on the ROHM website and check the contents carefully.
C8: https://www.rohm.com/products/power-management/switching-regulators/integrated-fet/buck-converters-nonsynchronous/bd9g500efj-la-product
A10: Note
C11: このファイルは、以下のデータシートRevに記載された計算式から作成されました。
D12: * このファイルの使用にあたっては、Licence Agreement に同意したものとみなされます。
D13: * 本計算シート内の計算式はあくまで理論式であり、実製品とのズレやばらつき、温度特性に関して考慮されているものではありません。
D14: * 詳細説明については、製品のデータシートを良くお読みください
C16: This file was created from the formula in the following datasheet Rev.
D17: * By using this file, you should agree to the "License Agreement".
D18: * The calculation formulas in this calculation sheet are theoretical formulas only, and are not considered for deviations, variations or temparaure characteristic from actual products.
D19: * Please read the product datasheet carefully for detailed explanation.
E21: BD9G500EFJ-LA
E22: 11.Jun.2020 Rev.001
A25: How to use
B26: (step 1)
C27: データシートの情報から周辺部品の暫定値を決めます。
D28: この計算シートはデータシートに記載されている回路理論式を計算します。
D29: 実際の評価ボードの特性や推奨定数は、IC内、基板の寄生成分や部品誤差などによって、理論式の計算結果と異なる場合があります。
D30: データシートにアプリケーション例または推奨部品リストが記載されている場合、製品ははこれらの使用条件に最適化されています。
D31: 出力設定や負荷値などの条件がご使用条件と同じ場合はデータシートの理論式の計算結果ではなく、この例や推奨リストの部品値を調整前の暫定値とします。
C33: Determine the temporary value of the external part from the information in the datasheet.
D34: This calculation sheet calculates the circuit theoretical formula described in the datasheet.
D35: Actual evaluation board characteristics and recommendation value may not match the results of the theoretical formula due to part and IC circuit errors and PCB parastic (accuracy, parasitics, etc.).
D36: If an application example (or recommended parts list) is included in the datasheet, the product is optimized for use under these conditions (output settings, load values, etc.).
D37: If these conditions and your usage conditions are the same, use the external part values in this example (or list) as temporary values before adjustment instead of the results of theoretical formula calculations.
C40: [ 1. Calculation sheet ]
D41: データシートに従って、各外付け部品の定数や条件を"value of external parts / customer's condition"にセットしていきます。
D42: （"internal typ value" は、製品内部で決まっている各種パラメータですが、初期状態ではTypical値を記載しています。
D43: ばらつき等を考慮する場合は、データシートの項目値に従って、入力してください。 ）
D45: Set the external part values and condition values in the "value of external parts / customer's condition" cell, referring to the explanation in the datasheet.
D46: ( "internal typ value" is an internal parameter of the product, and the cell initial value is set to the typical value.
D47: When considering the variation in the values, refer to the electrical characteristics table in the datasheet.)
C50: [ 2. Caluclation summery ]
D51: 1. Calculation sheetで計算した結果のまとめです。
D52: (2) Design parameter に、"1. Calculation sheet"で設定された諸特性がまとめられています。
D53: （NG項目があれば、"1. Calculation sheet"に戻り、外付け定数や条件を見直してください。）
D55: This sheet is a summary of the results calculated in "1. Calculation sheet".
D56: Each characteristic set in "1. Calculation sheet" is summarized in "(2) Design parameter".
D57: ( If there is an NG item, return to "1. Calculation sheet" and review the values and conditions of the external parts. )
B60: (step 2)
C61: 実際の評価ボードで製品を評価します。
D62: 実際の評価ボードで特性を必ず評価して下さい。（試作基板の回路図を決定する前に、実際の評価ボードで特性を確認することを強くお勧めします。）
D63: 特性の改善が必要な場合は、外付け部品などの値を調整して目的に近づけます。
D64: 決定された部品の値を使用して、試作基板でも特性が問題ないか評価します。
C66: Evaluate the product on the actual evaluation board.
D67: You must evaluate the characteristics on a real evaluation board.
D68: (Before deciding the parts of your prototype board, it is highly recommended to check the characteristics on an actual evaluation board. )
D69: If you need to improve the characteristics, adjust the external part values and conditions to get closer to your target.
D70: Using the determined part values, also check the characteristics of your prototype board.

Sheet 1. Calculation sheet
A1: ='How to use'!A1 -> BD9G500EFJ-LA Calculation Sheet | N1: ='How to use'!M1 -> REV.001 20210827
N2: ='How to use'!M2 -> ©2021 ROHM Co., LTD.
B3: この計算シートはデータシートに記載されている理論式を計算します。
B4: 実際の評価ボードの特性は、寄生や部品誤差などによって、理論式の計算結果と異なる場合があります。
B5: 特に入力コンデンサ、出力コンデンサの容量値については、温度特性やDCバイアス特性などを考慮して値を選定してください。
B6: 最終的には、実際の評価ボードで特性を必ず評価して下さい。また、特性の調整が必要な場合は目的の特性に近づける為に周辺部品の値や条件を調整して下さい。
B8: This calculation sheet calculates the theoretical formula described in the data sheet.
B9: Actual evaluation board characteristics may not match the results of the theoretical formula due to part errors (accuracy, parasitics, etc.).
B10: The capacitance values of the input and output capacitors should be selected in consideration of the temperature characteristics and DC bias characteristics.
B11: It is highly recommended to check the characteristics on an actual evaluation board. If you need to improve the characteristics, adjust the external part values and conditions to get closer to your target.
G13: :auto calculated value
G14: :value of external parts / customer's condition
G15: :internal typ value
F16: (*) | G16: :Setting range is limited
B19: Output Voltage Setting
C20: p.28, Output Voltage Set Point.
C21: p.17, Table 2. Recommended Component Values.
C22: Design Parameters | D22: Symbols | E22: Values | F22: Unit | G22: Recommendation
C23: Input Voltage designed value | D23: VIN | E23: 48 | F23: V (*) | G23: 7V to 76V
C24: Output Voltage design target | D24: VOUT (target) | E24: 40 | F24: V (*) | G24: 1.0V to 0.97xVINV
C25: Feedback resistors | D25: R6 | E25: 0 | F25: Ω (*)
D26: R2 | E26: 1 | F26: kΩ (*)
D27: R3 | E27: 39 | F27: kΩ (*)
C28: Output Voltage designed value | D28: VOUT | E28: =E39 -> 40 | F28: V | G28: 1.0V to 0.97xVINV
C30: Please make sure "Output Voltage designed value" satisfy your criteria of "Output Voltage designed target".
C33: Design constants | D33: Symbols | E33: Values | F33: Unit
C34: Feedback voltage | D34: VFB (typ) | E34: 1 | F34: V
E39: =((E25/1000+E26+E27)/E26) -> 40 | F39: V | M39: Judge: | N39: =IF(AND(E39>=1,E39<=E23*0.97),"OK","NG") -> OK
B46: Output LC Filter
C48: p.26, Output LC Filter.
C49: Design Parameters | D49: Symbols | E49: Values | F49: Unit | G49: Recommendation
C50: LC filter L inductance | D50: L (L1) | E50: 22 | F50: µH | G50: 33 µH | S50: $E$96>=$E$62 | T50: $E$96<$E$62 | U50: IL_START is higher than OCPmin.
C51: LC filter L saturation current required | D51: ISAT | E51: =E75 -> 5.7575758 | F51: A | U51: Adjust L, COUT, and/or CLOAD.
C53: LC filter C capacitance | D53: C6 | E53: 10 | F53: µF | G53: Output Capacitor | S53: $E$96>=$E$62 | T53: $E$96<$E$62
D54: C7 | E54: 120 | F54: µF | S54: $E$96>=$E$62 | T54: $E$96<$E$62
C55: LC filter C serial equivalent series resistance | D55: RESR | E55: 28 | F55: mΩ
C56: Load capacitance connected to VOUT | D56: CLOAD | E56: 0 | F56: µF (*1) | G56: < CLOAD(max) = | H56: =E111 -> 79.343434 | I56: µF | S56: OR($E$54>$H$54,$E$96>=$E$62) | T56: AND($E$54<=$H$54, $E$96<$E$62) | U56: Cload should be less than Cloadmax.
C57: Maximum Output Current | D57: IOUTMAX | E57: 5 | F57: A (*1) | G57: up to 5A | S57: >5 | T57: <=5 | U57: IOUTMAX is out of range. (up to 5A only)
C59: Design constants | D59: Symbols | E59: Values | F59: Unit
C60: Switching Frequency | D60: fOSC (typ) | E60: 200 | F60: kHz
D61: fOSC (min) | E61: 180 | F61: kHz
C62: Soft Start Time | D62: tSS (min) | E62: 15 | F62: ms
C63: Over Current limit | D63: ILIMIT (min) | E63: 6.4 | F63: A
C66: Inductor ripple current:
E69: =E28*(E23-E28)*(1/(E23*E60/1000*E50)) -> 1.5151515 | F69: A
C72: Note:
C73: Also for saturation current of inductor, select the one with larger current than the total of maximum output current and 1/2 of inductor ripple current ΔIL. Also for saturation current of catch diode.
E75: =E57+E69/2 -> 5.7575758 | F75: A
C78: Output ripple voltage:
C79: When selecting the value of the output capacitor COUT, please note that the value of capacitor CLOAD will add up to the value of COUT to be connected to VOUT.
E82: =(E69*((E55/1000)+(1/(8*(E53+E54)*E60/1000))))*1000 -> 49.708625 | F82: mV
C85: Inductor ripple current maximum value at start-up:
C86: IL_START can be expressed as follows.
C88: Here, IOUTMAX is Maximum Output Current, and ICAP is charging current to the output capacitors.
C89: (Note) Maximum starting inductor ripple current IL_START must smaller than over current limit 6.4 A (Min).
E91: =((E53+E54+E56)/1000000*E28)/(E62/1000) -> 0.34666667 | F91: A
E97: =E57+(E69/2)+E91 -> 6.1042424 | F97: ="A < "&E63&" A" -> A < 6,4 A | M97: Judge: | N97: =IF(E97<E63,"OK","NG") -> OK
C101: Maximum output load capacitance (CLOAD (max)):
C103: In order to estimate CLOAD (max), maximum value of inductor ripple current has to be taken into account.
D106: (max) = | E106: =E28*(E23-E28)*(1/(E23*E61/1000*E50)) -> 1.6835017 | F106: A
C108: Note) minimum value for FOSC is used.
E111: =(((E63-E57-E106/2)*(E62/1000))/E28)*1000000-SUM(E53:E54) -> 79.343434 | F111: µF | G111: = | H111: =E56 -> 0 | I111: µF | M111: Judge: | N111: =IF(H111<E111,"OK","NG") -> OK
B117: Switching Frequency
C119: p.26, Switching Frequency.
C120: Design Parameters | D120: Symbols | E120: Values | F120: Unit | G120: Recommendation
C121: Switching Frequency Using RT Pin | D121: fRTOSC | E121: =E132 -> 392.76963 | F121: kHz | G121: 200 kHz (typ); 100 kHz to 650 kHz | S121: not bet $E$124 $E$125
C122: RT resistance | D122: RRT (R4) | E122: 22 | F122: kΩ (*) | G122: ="47 kΩ (typ); "&E128&" kΩ to "&E130&" kΩ" -> 47 kΩ (typ); 12,5 kΩ to 102 kΩ | S122: not bet $E$127 $E$129 | T122: bet E127 E129 | U122: RRT (R4) is not valid. fOSC is out of range.
C124: Design constants | D124: Symbols | E124: Values | F124: Unit
C125: Switching Frequency Range Using RT Pin | D125: fRTOSC (min) | E125: 100 | F125: kHz
D126: fRTOSC (max) | E126: 650 | F126: kHz
D128: (min) = | E128: =ROUNDUP(18423/(E126^1.127),1) -> 12.5 | F128: kΩ
D130: (max) = | E130: =ROUNDDOWN(18423/(E125^1.127),0) -> 102 | F130: kΩ
M131: Judge: | N131: =IF(AND(E121>=E125,E121<=E126),"OK","NG") -> OK
E132: =6093.5/(E122^0.887) -> 392.76963 | F132: kHz
B137: Phase Compensation
C138: p.28, Phase Compensation.
C140: (*1) Input the target crossover frequency fCRS. Recommended value is 1/10 to 1/50 of fOSC.
C141: (*2) Input the value of target fZ (zero point), which is recommended to smaller than fCRS/9.
C142: Design parameters | D142: Symbols | E142: Values | F142: Unit
C143: Target vaule of crossover frequency | D143: fCRS (target) | E143: 9 | F143: kHz (*1) | S143: not bet E58/50 E58/10 | T143: AND(E141>=(E58/50),E141<=(E58/10))
C144: Target vaule of zero frequency | D144: fZ (target) | E144: 0.5 | F144: kHz (*2) | S144: $E$142>=E$141/9 | T144: < E141/9
C147: Internal parameters listed in the table below are refered to calculate RCMP and CCMP.
C148: Internal parameters | D148: Symbols | E148: Values | F148: Units
C149: Current sense gain | D149: GMP (typ) | E149: 14 | F149: A/V
C150: Error amplifier trans conductance | D150: GMA (typ) | E150: 200 | F150: µA/V
C152: Phase Compensation Resistor (R1)
C153: Target value of R1 can be calculated from the crossover frequency fCRS by the following equation.
M155: Symbols | N155: Values | O155: Units | P155: %error
D156: = | E156: =((2*PI()*E28*(E143*1000)*(SUM(E53:E54)/1000000))/(E34*E149*E150/1000000))/1000 -> 105.01895 | F156: kΩ | L156: Fill R1 value based on the calculation result --> | M156: R1 | N156: 110 | O156: kΩ | P156: =(N156-E156)/E156 -> 0.047429967 | S156: error>5%
L157: Calculated fCRS from R1 | M157: fCRS | N157: =((N156*1000*E34*E149*E150/1000000) / (2*PI()*E28*(SUM(E53:E54)/1000000)))/1000 -> 9.4268697 | O157: kHz | P157: =(N157-E143)/E143 -> 0.047429967 | S157: error>5%
K158: (note) fCRS is highligted when absolute value of % error against the target excess 5%.
C159: Phase Compensation Capacitor (C2)
C160: Target value of C2 can be calculated from the zero frequency fZ by the following equation.
M162: Symbols | N162: Values | O162: Units | P162: %error
D163: = | E163: =(1/(2*PI()*E156*1000*E144*1000))*1000000000000 -> 3030.9756 | F163: pF | L163: Fill C2 value based on the calculation result --> | M163: C2 | N163: 3300 | O163: pF | P163: =(N163-E163)/E163 -> 0.08875836 | S163: error>5% | T163: OR(ABS($P$161)>5%,$N$161<$E$161)
L164: Calculated fZ from C2 | M164: fz | N164: =(E34*E149*E150/1000000)/(2*PI()*E28*SUM(E53:E54)/1000000*2*PI()*N163/1000000000000*E144*1000*9)/1000 -> 0.91847745 | O164: kHz | P164: =(N164-E144)/E144 -> 0.8369549 | S164: error>5% | T164: (E32*E147*E148/1000000)/(2*PI()*E26*SUM(E51:E52)/1000000*2*PI()*N161/1000000000000*E142*1000*9)/1000
K165: (note) fZ is highligted when absolute value of % error against the target excess 5%. | T165: 1/(2*PI()*E154*N161/1000000)
C166: For stable operation of the DC/DC converter, inserting a zero point under 1/9 of zero crossover frequency fCRS
C167: cancels the phase delay due to the pole formed by the load often provides favorable characteristics.
B169: Notes:
...

Sheet 2. Calculation summary
A1: Summary : | C1: ='How to use'!A1 -> BD9G500EFJ-LA Calculation Sheet | S1: ='How to use'!M1 -> REV.001 20210827
S2: ='How to use'!M2 -> ©2021 ROHM Co., LTD.
B3: この計算シートはデータシートに記載されている理論式を計算します。
B4: 実際の評価ボードの特性は、寄生や部品誤差などによって、理論式の計算結果と異なる場合があります。
B5: 最終的には、実際の評価ボードで特性を必ず評価して下さい。また、特性の調整が必要な場合は目的の特性に近づける為に周辺部品の値や条件を調整して下さい。
B7: This calculation sheet calculates the theoretical formula described in the data sheet.
B8: Actual evaluation board characteristics may not match the results of the theoretical formula due to part errors (accuracy, parasitics, etc.).
B9: It is highly recommended to check the characteristics on an actual evaluation board. If you need to improve the characteristics, adjust the external part values and conditions to get closer to your target.
F11: :Value from 1. Calculation sheet
B13: (1) Peripheral component parameters
C15: Component Parameters | F15: Value | G15: Units | H15: Judge | I15: Conditions
C16: ='1. Calculation sheet'!D25 -> R6 | F16: ='1. Calculation sheet'!$E$25 -> 0 | G16: Ω | H16: -
C17: ='1. Calculation sheet'!D26 -> R2 | F17: ='1. Calculation sheet'!$E$26 -> 1 | G17: kΩ | H17: -
C18: ='1. Calculation sheet'!$D$27 -> R3 | F18: ='1. Calculation sheet'!$E$27 -> 39 | G18: kΩ | H18: -
C19: L1 | D19: Inductance | F19: ='1. Calculation sheet'!$E$50 -> 22 | G19: µH | H19: - | I19: ='1. Calculation sheet'!G50 -> 33 µH
D20: ISAT | F20: ='1. Calculation sheet'!$E$51 -> 5.7575758 | G20: A | H20: -
C21: Cout | D21: ='1. Calculation sheet'!D53 -> C6 | F21: ='1. Calculation sheet'!$E$53 -> 10 | G21: µF | H21: -
D22: ='1. Calculation sheet'!D54 -> C7 | F22: ='1. Calculation sheet'!$E$54 -> 120 | G22: µF | H22: -
D23: RESR | F23: ='1. Calculation sheet'!$E$55 -> 28 | G23: mΩ | H23: -
C24: R4 | F24: ='1. Calculation sheet'!E122 -> 22 | G24: kΩ | H24: - | I24: ='1. Calculation sheet'!G122 -> 47 kΩ (typ); 12,5 kΩ to 102 kΩ
C25: ='1. Calculation sheet'!M156 -> R1 | F25: ='1. Calculation sheet'!$N$156 -> 110 | G25: kΩ | H25: -
C26: ='1. Calculation sheet'!M163 -> C2 | F26: ='1. Calculation sheet'!N163 -> 3300 | G26: pF | H26: -
C27: C4 | F27: 15 | G27: µF | H27: -
C28: C9 | F28: 1 | G28: µF | H28: -
C29: C3 | F29: 1 | G29: µF | H29: -
C30: R5 | F30: 0 | G30: Ω | H30: -
C31: D1 | F31: 100 | G31: V | H31: -
B33: (2) Design Parameter
C34: Item | E34: Symbols | F34: Values | G34: Units | H34: Judge | I34: Conditions
C35: Input Voltage | E35: VIN | F35: ='1. Calculation sheet'!E23 -> 48 | G35: V | H35: - | I35: ='1. Calculation sheet'!G23 -> 7V to 76V
C36: Output Voltage | E36: VOUT | F36: ='1. Calculation sheet'!E39 -> 40 | G36: V | H36: ='1. Calculation sheet'!N39 -> OK | I36: ='1. Calculation sheet'!G24 -> 1.0V to 0.97xVINV
C37: Maximum output current | E37: IOUTMAX | F37: ='1. Calculation sheet'!E57 -> 5 | G37: A | H37: -
C38: Load capacitance connected to VOUT | E38: CLOAD | F38: ='1. Calculation sheet'!E56 -> 0 | G38: µF | H38: ='1. Calculation sheet'!N111 -> OK | J38: CLOAD ≦CLOAD(max) = | K38: ='1. Calculation sheet'!E111 -> 79.343434
C39: Crossover frequency design target | E39: fCRS (target) | F39: ='1. Calculation sheet'!E143 -> 9 | G39: kHz | H39: -
C40: Zero frequency design target | E40: fZ (target) | F40: ='1. Calculation sheet'!E144 -> 0.5 | G40: kHz | H40: -
B42: (3) Calculation results
C43: Item | E43: Symbols | F43: Values | G43: Units | H43: Judge | I43: Conditions
C44: Output LC Filter | D44: Inductor Ripple Current | E44: ΔIL | F44: ='1. Calculation sheet'!E69 -> 1.5151515 | G44: A | H44: -
D45: Output Ripple Voltage | E45: ΔVRPL | F45: ='1. Calculation sheet'!E82 -> 49.708625 | G45: mV | H45: -
D46: Charging current to output capacitors | E46: ICAP | F46: ='1. Calculation sheet'!E91 -> 0.34666667 | G46: A | H46: -
D47: Inductor ripple current (max) of start-up | E47: IL_START | F47: ='1. Calculation sheet'!$E$97 -> 6.1042424 | G47: A | H47: ='1. Calculation sheet'!$N$97 -> OK | I47: ="< "&'1. Calculation sheet'!E63&" A" -> < 6,4 A
C48: ='1. Calculation sheet'!C121 -> Switching Frequency Using RT Pin | E48: fRTOSC | F48: ='1. Calculation sheet'!E132 -> 392.76963 | G48: kHz | H48: ='1. Calculation sheet'!N131 -> OK | I48: ='1. Calculation sheet'!G121 -> 200 kHz (typ); 100 kHz to 650 kHz
C49: Phase | D49: R1 target value | E49: R1 | F49: ='1. Calculation sheet'!E156 -> 105.01895 | G49: kΩ | H49: -
C50: Compensation | D50: C2 target value | E50: C2 | F50: ='1. Calculation sheet'!E163 -> 3030.9756 | G50: pF | H50: -
D51: Crossover frequency | E51: ｆCRS | F51: ='1. Calculation sheet'!N157 -> 9.4268697 | G51: kHz | H51: -
D52: Zero frequency | E52: ｆZ | F52: ='1. Calculation sheet'!N164 -> 0.91847745 | G52: kHz | H52: -
I55: NGがある場合は、定数設定を見直す必要があります。
I56: If there is NG, it is necessary to review the constant setting.

Sheet rev history
B4: REV | C4: Date | D4: Overview
B5: 001 | C5: 23.Feb.2021 | D5: New Release
B6: 002 | C6: 27.Aug.2021 | D6: Updated How to use sheet, Added Link to website.
